pier_cli/__init__.py
pier_cli/utils.py
pier_cli/cli/__init__.py
pier_cli/cli/run.py
pier_cli/models/__init__.py
pier_cli/models/docker/__init__.py
pier_cli/models/docker/image.py
pier_cli/models/kubernetes/__init__.py
pier_cli/models/kubernetes/deployment.py
pier_cli/models/kubernetes/pod.py
pier_cli/services/__init__.py
pier_cli/services/docker_service.py
pier_cli/services/pod_service.py
pier_cli-0.0.3.dist-info/LICENSE
pier_cli-0.0.3.dist-info/METADATA
pier_cli-0.0.3.dist-info/WHEEL
pier_cli-0.0.3.dist-info/entry_points.txt
pier_cli-0.0.3.dist-info/top_level.txt
pier_cli-0.0.3.dist-info/RECORD
