Metadata-Version: 2.1
Name: pier-cli
Version: 0.0.3
Summary: pier-cli is a development tool that provides an easy way to deploy your local images to Kubernetes
Home-page: UNKNOWN
Author: Marten Sies
License: UNKNOWN
Platform: UNKNOWN
Classifier: Programming Language :: Python :: 3
Classifier: License :: OSI Approved :: MIT License
Classifier: Operating System :: OS Independent
Classifier: Intended Audience :: Developers
Classifier: Environment :: Console
Provides: pier
Requires-Python: >=3.6
Requires-Dist: docker
Requires-Dist: kubernetes
Requires-Dist: fire
Requires-Dist: tabulate
